surmado/__init__.py
surmado/client.py
surmado-0.1.2.dist-info/METADATA
surmado-0.1.2.dist-info/WHEEL
surmado-0.1.2.dist-info/licenses/LICENSE
surmado-0.1.2.dist-info/RECORD
