Metadata-Version: 2.4
Name: surmado
Version: 0.1.2
Summary: Official Python client for Surmado's AI visibility testing and SEO reports
Project-URL: Homepage, https://surmado.com
Project-URL: Documentation, https://help.surmado.com/docs/api-reference/
Project-URL: Repository, https://github.com/surmado/surmado-python
Project-URL: Issues, https://github.com/surmado/surmado-python/issues
Project-URL: Changelog, https://github.com/surmado/surmado-python/blob/main/CHANGELOG.md
Author-email: Surmado Engineering <engineering@surmado.com>
License-Expression: MIT
License-File: LICENSE
Keywords: ai,analytics,chatgpt,geo,llm,marketing,perplexity,seo,surmado,visibility
Classifier: Development Status :: 4 - Beta
Classifier: Intended Audience :: Developers
Classifier: License :: OSI Approved :: MIT License
Classifier: Operating System :: OS Independent
Classifier: Programming Language :: Python :: 3
Classifier: Programming Language :: Python :: 3.8
Classifier: Programming Language :: Python :: 3.9
Classifier: Programming Language :: Python :: 3.10
Classifier: Programming Language :: Python :: 3.11
Classifier: Programming Language :: Python :: 3.12
Classifier: Topic :: Internet :: WWW/HTTP
Classifier: Topic :: Software Development :: Libraries :: Python Modules
Requires-Python: >=3.8
Requires-Dist: requests>=2.25.0
